kickstart_flask_app/__init__.py
kickstart_flask_app/core.py
kickstart_flask_app/templates.py
kickstart_flask_app-1.2.0.dist-info/LICENSE
kickstart_flask_app-1.2.0.dist-info/METADATA
kickstart_flask_app-1.2.0.dist-info/WHEEL
kickstart_flask_app-1.2.0.dist-info/entry_points.txt
kickstart_flask_app-1.2.0.dist-info/top_level.txt
kickstart_flask_app-1.2.0.dist-info/RECORD
