Metadata-Version: 2.1
Name: kickstart_flask_app
Version: 1.2.0
Summary: Generate a new Flask app project.
Author-email: Majdi Mahfoud <elm.majidi@gmail.com>
Project-URL: Bug Tracker, https://github.com/MurphyAdam/kickstart-flask-app/issues
Project-URL: Homepage, https://github.com/MurphyAdam/kickstart-flask-app
Classifier: Programming Language :: Python
Classifier: Programming Language :: Python :: 3.8
Requires-Python: >=3.8
License-File: LICENSE
Requires-Dist: flask >=3.0.0
